freshpointsync/__init__.py
freshpointsync/_logging.py
freshpointsync/py.typed
freshpointsync/client/__init__.py
freshpointsync/client/_client.py
freshpointsync/page/__init__.py
freshpointsync/page/_page.py
freshpointsync/parser/__init__.py
freshpointsync/parser/_parser.py
freshpointsync/product/__init__.py
freshpointsync/product/_product.py
freshpointsync/runner/__init__.py
freshpointsync/runner/_runner.py
freshpointsync/update/__init__.py
freshpointsync/update/_update.py
FreshPointSync-0.2.1.dist-info/LICENSE
FreshPointSync-0.2.1.dist-info/METADATA
FreshPointSync-0.2.1.dist-info/WHEEL
FreshPointSync-0.2.1.dist-info/top_level.txt
FreshPointSync-0.2.1.dist-info/RECORD
