Metadata-Version: 2.1
Name: FreshPointSync
Version: 0.2.1
Summary: FreshPoint webpage data parser and syncer.
Author-email: Konstantin Mykhailov <constantinemykhailov@gmail.com>
License: MIT License
Project-URL: Homepage, https://github.com/mykhakos/FreshPointSync
Keywords: freshpoint,freshpoint.cz
Classifier: Development Status :: 3 - Alpha
Classifier: Framework :: aiohttp
Classifier: Framework :: AsyncIO
Classifier: Intended Audience :: Developers
Classifier: Intended Audience :: Other Audience
Classifier: License :: OSI Approved :: MIT License
Classifier: Natural Language :: English
Classifier: Natural Language :: Czech
Classifier: Operating System :: OS Independent
Classifier: Programming Language :: Python :: 3
Classifier: Programming Language :: Python :: 3 :: Only
Classifier: Programming Language :: Python :: 3.8
Classifier: Programming Language :: Python :: 3.9
Classifier: Programming Language :: Python :: 3.10
Classifier: Programming Language :: Python :: 3.11
Classifier: Programming Language :: Python :: 3.12
Classifier: Topic :: Internet
Classifier: Topic :: Software Development :: Libraries :: Python Modules
Classifier: Topic :: Text Processing :: Markup :: HTML
Classifier: Typing :: Typed
Requires-Python: >=3.8
License-File: LICENSE
Requires-Dist: aiohttp >=3.7
Requires-Dist: certifi >=2020.4.5
Requires-Dist: beautifulsoup4 >=4.9
Requires-Dist: lxml >=4.5
Requires-Dist: pydantic >=2.0
Requires-Dist: unidecode >=1.3
Requires-Dist: typing-extensions >=4.3 ; python_version < "3.10"
Provides-Extra: build
Requires-Dist: build ; extra == 'build'
Requires-Dist: twine ; extra == 'build'
Provides-Extra: dev
Requires-Dist: tox ; extra == 'dev'
Requires-Dist: freshpointsync[lint] ; extra == 'dev'
Requires-Dist: freshpointsync[test] ; extra == 'dev'
Requires-Dist: freshpointsync[doc] ; extra == 'dev'
Requires-Dist: freshpointsync[build] ; extra == 'dev'
Provides-Extra: docs
Requires-Dist: sphinx ; extra == 'docs'
Requires-Dist: sphinx-copybutton ; extra == 'docs'
Requires-Dist: autodoc-pydantic ; extra == 'docs'
Requires-Dist: sphinx-rtd-theme ; extra == 'docs'
Provides-Extra: lint
Requires-Dist: mypy ; extra == 'lint'
Requires-Dist: ruff ; extra == 'lint'
Provides-Extra: test
Requires-Dist: pytest ; extra == 'test'
Requires-Dist: pytest-asyncio ; extra == 'test'
